{
  "tiles": [
    [
      "",
      "0",
      "",
      "",
      "b",
      ""
    ],
    [
      "b",
      "a",
      "a",
      "b",
      "a",
      "0"
    ],
    [
      "",
      "c",
      "d",
      "",
      "d",
      ""
    ],
    [
      "",
      "c",
      "",
      "d",
      "0",
      ""
    ],
    [
      "0",
      "a",
      "0",
      "b",
      "d",
      "c"
    ],
    [
      "",
      "c",
      "",
      "",
      "0",
      ""
    ]
  ],
  "completed": false,
  "swaps": 3,
  "rows": 6,
  "cols": 6
}